{
  "status": "completed_with_errors",
  "started_at": "2026-07-23T13:15:03+09:00",
  "last_updated_at": "2026-07-23T13:16:00+09:00",
  "finished_at": "2026-07-23T13:16:00+09:00",
  "spec_path": "D:\\project\\TVBPerf\\scripts\\scene_geom_ex2.json",
  "spec_copy": "D:\\project\\TVBPerf\\scripts\\results\\scene_geom_ex2\\scene_geom_ex2.json",
  "output_csv": "D:\\project\\TVBPerf\\scripts\\results\\scene_geom_ex2\\scene_geom_ex2.csv",
  "report_json": "D:\\project\\TVBPerf\\scripts\\results\\scene_geom_ex2\\scene_geom_ex2_run_report.json",
  "completed_runs": 18,
  "successful_runs": 0,
  "salvaged_runs": 18,
  "failed_runs": 0,
  "runs": [
    {
      "run_index": 0,
      "repeat": 0,
      "status": "salvaged",
      "started_at": "2026-07-23T13:15:03+09:00",
      "finished_at": "2026-07-23T13:15:06+09:00",
      "return_code": 0,
      "command": [
        "D:\\project\\TVBPerf\\out\\build\\x64-Release\\bin\\Release\\TVBPerf.exe",
        "--run-id",
        "0",
        "--run-name",
        "scene_geom_ex2",
        "--output-filepath",
        "C:\\Users\\mgkim15\\AppData\\Local\\Temp\\tvbperf_9cgy38ir\\run_00000.csv",
        "--renderer-variant",
        "1",
        "--variable",
        "0",
        "--to-use-scene",
        "1",
        "--to-load-texture",
        "0",
        "--use-vfc",
        "1",
        "--scene-path",
        "assets/scenes/unpacked/main_sponza/NewSponza_Main_glTF_003.gltf",
        "--warmup-frames",
        "60",
        "--measure-frames",
        "2400",
        "--auto-terminate",
        "1",
        "--vsync",
        "0",
        "--camera-mode",
        "2",
        "--camera-filepath",
        "standard_camera.csv",
        "--camera-keyframe-interval",
        "10",
        "--to-set-start-frame",
        "0",
        "--key-frame",
        "0",
        "--profile-window-frames",
        "10",
        "--window-width",
        "1920",
        "--window-height",
        "1080",
        "--seed",
        "0",
        "--camera-pos-x",
        "0.0",
        "--camera-pos-y",
        "0.0",
        "--camera-pos-z",
        "-10.0",
        "--camera-lookat-x",
        "0.0",
        "--camera-lookat-y",
        "0.0",
        "--camera-lookat-z",
        "0.0",
        "--camera-near-z",
        "0.1",
        "--camera-far-z",
        "1000.0",
        "--camera-fov",
        "0.785",
        "--object-count",
        "1",
        "--material-count",
        "1",
        "--geometry-count",
        "1",
        "--overdraw-count",
        "0",
        "--to-remain-only-in-camera",
        "0",
        "--z-min",
        "-1.0",
        "--z-max",
        "1.0",
        "--xy-minmax",
        "1.0",
        "--radius",
        "0.5",
        "--geometry-div",
        "1",
        "--gbuffer-cnt",
        "1",
        "--texture-count",
        "1",
        "--texture-size",
        "256",
        "--texture-sampling-count",
        "1",
        "--alu-calc-count",
        "1"
      ],
      "parameters": {
        "run_id": 0,
        "run_name": "no-run-name",
        "output_filepath": "profile_result.csv",
        "variable": 0,
        "to_use_scene": true,
        "to_load_texture": false,
        "use_vfc": true,
        "scene_path": "assets/scenes/unpacked/main_sponza/NewSponza_Main_glTF_003.gltf",
        "warmup_frames": 60,
        "measure_frames": 2400,
        "auto_terminate": true,
        "vsync": false,
        "camera_mode": 2,
        "camera_filepath": "standard_camera.csv",
        "camera_keyframe_interval": 10,
        "to_set_start_frame": false,
        "key_frame": 0,
        "profile_window_frames": 10,
        "window_width": 1920,
        "window_height": 1080,
        "seed": 0,
        "camera_pos_x": 0.0,
        "camera_pos_y": 0.0,
        "camera_pos_z": -10.0,
        "camera_lookat_x": 0.0,
        "camera_lookat_y": 0.0,
        "camera_lookat_z": 0.0,
        "camera_near_z": 0.1,
        "camera_far_z": 1000.0,
        "camera_fov": 0.785,
        "object_count": 1,
        "material_count": 1,
        "geometry_count": 1,
        "overdraw_count": 0,
        "to_remain_only_in_camera": false,
        "z_min": -1.0,
        "z_max": 1.0,
        "xy_minmax": 1.0,
        "radius": 0.5,
        "geometry_div": 1,
        "gbuffer_cnt": 1,
        "texture_count": 1,
        "texture_size": 256,
        "texture_sampling_count": 1,
        "renderer_variant": 1,
        "alu_calc_count": 1
      },
      "raw_csv": "C:\\Users\\mgkim15\\AppData\\Local\\Temp\\tvbperf_9cgy38ir\\run_00000.csv",
      "individual_csv": "D:\\project\\TVBPerf\\scripts\\results\\scene_geom_ex2\\scene_geom_ex2_runs\\run_00000.csv",
      "artifact_csvs": [
        "D:\\project\\TVBPerf\\scripts\\results\\scene_geom_ex2\\scene_geom_ex2_runs\\run_00000.csv_0_result.csv",
        "D:\\project\\TVBPerf\\scripts\\results\\scene_geom_ex2\\scene_geom_ex2_runs\\run_00000_scene_fingerprint.csv"
      ],
      "raw_row_count": 1,
      "error": "Log saved to: D:\\project\\TVBPerf\\out\\build\\x64-Release\\bin\\Release\\logs\\log_2026-07-23_13-15-06.txt",
      "csv_write_error": null,
      "individual_copy_error": null,
      "artifact_copy_errors": []
    },
    {
      "run_index": 1,
      "repeat": 0,
      "status": "salvaged",
      "started_at": "2026-07-23T13:15:06+09:00",
      "finished_at": "2026-07-23T13:15:09+09:00",
      "return_code": 0,
      "command": [
        "D:\\project\\TVBPerf\\out\\build\\x64-Release\\bin\\Release\\TVBPerf.exe",
        "--run-id",
        "1",
        "--run-name",
        "scene_geom_ex2",
        "--output-filepath",
        "C:\\Users\\mgkim15\\AppData\\Local\\Temp\\tvbperf_9cgy38ir\\run_00001.csv",
        "--renderer-variant",
        "1",
        "--variable",
        "0",
        "--to-use-scene",
        "1",
        "--to-load-texture",
        "0",
        "--use-vfc",
        "1",
        "--scene-path",
        "assets/scenes/unpacked/main_sponza/NewSponza_Main_glTF_003.gltf",
        "--warmup-frames",
        "60",
        "--measure-frames",
        "2400",
        "--auto-terminate",
        "1",
        "--vsync",
        "0",
        "--camera-mode",
        "2",
        "--camera-filepath",
        "standard_camera.csv",
        "--camera-keyframe-interval",
        "10",
        "--to-set-start-frame",
        "0",
        "--key-frame",
        "0",
        "--profile-window-frames",
        "10",
        "--window-width",
        "1920",
        "--window-height",
        "1080",
        "--seed",
        "0",
        "--camera-pos-x",
        "0.0",
        "--camera-pos-y",
        "0.0",
        "--camera-pos-z",
        "-10.0",
        "--camera-lookat-x",
        "0.0",
        "--camera-lookat-y",
        "0.0",
        "--camera-lookat-z",
        "0.0",
        "--camera-near-z",
        "0.1",
        "--camera-far-z",
        "1000.0",
        "--camera-fov",
        "0.785",
        "--object-count",
        "1",
        "--material-count",
        "1",
        "--geometry-count",
        "1",
        "--overdraw-count",
        "0",
        "--to-remain-only-in-camera",
        "0",
        "--z-min",
        "-1.0",
        "--z-max",
        "1.0",
        "--xy-minmax",
        "1.0",
        "--radius",
        "0.5",
        "--geometry-div",
        "1",
        "--gbuffer-cnt",
        "1",
        "--texture-count",
        "1",
        "--texture-size",
        "256",
        "--texture-sampling-count",
        "1",
        "--alu-calc-count",
        "2"
      ],
      "parameters": {
        "run_id": 0,
        "run_name": "no-run-name",
        "output_filepath": "profile_result.csv",
        "variable": 0,
        "to_use_scene": true,
        "to_load_texture": false,
        "use_vfc": true,
        "scene_path": "assets/scenes/unpacked/main_sponza/NewSponza_Main_glTF_003.gltf",
        "warmup_frames": 60,
        "measure_frames": 2400,
        "auto_terminate": true,
        "vsync": false,
        "camera_mode": 2,
        "camera_filepath": "standard_camera.csv",
        "camera_keyframe_interval": 10,
        "to_set_start_frame": false,
        "key_frame": 0,
        "profile_window_frames": 10,
        "window_width": 1920,
        "window_height": 1080,
        "seed": 0,
        "camera_pos_x": 0.0,
        "camera_pos_y": 0.0,
        "camera_pos_z": -10.0,
        "camera_lookat_x": 0.0,
        "camera_lookat_y": 0.0,
        "camera_lookat_z": 0.0,
        "camera_near_z": 0.1,
        "camera_far_z": 1000.0,
        "camera_fov": 0.785,
        "object_count": 1,
        "material_count": 1,
        "geometry_count": 1,
        "overdraw_count": 0,
        "to_remain_only_in_camera": false,
        "z_min": -1.0,
        "z_max": 1.0,
        "xy_minmax": 1.0,
        "radius": 0.5,
        "geometry_div": 1,
        "gbuffer_cnt": 1,
        "texture_count": 1,
        "texture_size": 256,
        "texture_sampling_count": 1,
        "renderer_variant": 1,
        "alu_calc_count": 2
      },
      "raw_csv": "C:\\Users\\mgkim15\\AppData\\Local\\Temp\\tvbperf_9cgy38ir\\run_00001.csv",
      "individual_csv": "D:\\project\\TVBPerf\\scripts\\results\\scene_geom_ex2\\scene_geom_ex2_runs\\run_00001.csv",
      "artifact_csvs": [
        "D:\\project\\TVBPerf\\scripts\\results\\scene_geom_ex2\\scene_geom_ex2_runs\\run_00001.csv_1_result.csv",
        "D:\\project\\TVBPerf\\scripts\\results\\scene_geom_ex2\\scene_geom_ex2_runs\\run_00001_scene_fingerprint.csv"
      ],
      "raw_row_count": 1,
      "error": "Log saved to: D:\\project\\TVBPerf\\out\\build\\x64-Release\\bin\\Release\\logs\\log_2026-07-23_13-15-09.txt",
      "csv_write_error": null,
      "individual_copy_error": null,
      "artifact_copy_errors": []
    },
    {
      "run_index": 2,
      "repeat": 0,
      "status": "salvaged",
      "started_at": "2026-07-23T13:15:09+09:00",
      "finished_at": "2026-07-23T13:15:12+09:00",
      "return_code": 0,
      "command": [
        "D:\\project\\TVBPerf\\out\\build\\x64-Release\\bin\\Release\\TVBPerf.exe",
        "--run-id",
        "2",
        "--run-name",
        "scene_geom_ex2",
        "--output-filepath",
        "C:\\Users\\mgkim15\\AppData\\Local\\Temp\\tvbperf_9cgy38ir\\run_00002.csv",
        "--renderer-variant",
        "1",
        "--variable",
        "0",
        "--to-use-scene",
        "1",
        "--to-load-texture",
        "0",
        "--use-vfc",
        "1",
        "--scene-path",
        "assets/scenes/unpacked/main_sponza/NewSponza_Main_glTF_003.gltf",
        "--warmup-frames",
        "60",
        "--measure-frames",
        "2400",
        "--auto-terminate",
        "1",
        "--vsync",
        "0",
        "--camera-mode",
        "2",
        "--camera-filepath",
        "standard_camera.csv",
        "--camera-keyframe-interval",
        "10",
        "--to-set-start-frame",
        "0",
        "--key-frame",
        "0",
        "--profile-window-frames",
        "10",
        "--window-width",
        "1920",
        "--window-height",
        "1080",
        "--seed",
        "0",
        "--camera-pos-x",
        "0.0",
        "--camera-pos-y",
        "0.0",
        "--camera-pos-z",
        "-10.0",
        "--camera-lookat-x",
        "0.0",
        "--camera-lookat-y",
        "0.0",
        "--camera-lookat-z",
        "0.0",
        "--camera-near-z",
        "0.1",
        "--camera-far-z",
        "1000.0",
        "--camera-fov",
        "0.785",
        "--object-count",
        "1",
        "--material-count",
        "1",
        "--geometry-count",
        "1",
        "--overdraw-count",
        "0",
        "--to-remain-only-in-camera",
        "0",
        "--z-min",
        "-1.0",
        "--z-max",
        "1.0",
        "--xy-minmax",
        "1.0",
        "--radius",
        "0.5",
        "--geometry-div",
        "1",
        "--gbuffer-cnt",
        "1",
        "--texture-count",
        "1",
        "--texture-size",
        "256",
        "--texture-sampling-count",
        "1",
        "--alu-calc-count",
        "4"
      ],
      "parameters": {
        "run_id": 0,
        "run_name": "no-run-name",
        "output_filepath": "profile_result.csv",
        "variable": 0,
        "to_use_scene": true,
        "to_load_texture": false,
        "use_vfc": true,
        "scene_path": "assets/scenes/unpacked/main_sponza/NewSponza_Main_glTF_003.gltf",
        "warmup_frames": 60,
        "measure_frames": 2400,
        "auto_terminate": true,
        "vsync": false,
        "camera_mode": 2,
        "camera_filepath": "standard_camera.csv",
        "camera_keyframe_interval": 10,
        "to_set_start_frame": false,
        "key_frame": 0,
        "profile_window_frames": 10,
        "window_width": 1920,
        "window_height": 1080,
        "seed": 0,
        "camera_pos_x": 0.0,
        "camera_pos_y": 0.0,
        "camera_pos_z": -10.0,
        "camera_lookat_x": 0.0,
        "camera_lookat_y": 0.0,
        "camera_lookat_z": 0.0,
        "camera_near_z": 0.1,
        "camera_far_z": 1000.0,
        "camera_fov": 0.785,
        "object_count": 1,
        "material_count": 1,
        "geometry_count": 1,
        "overdraw_count": 0,
        "to_remain_only_in_camera": false,
        "z_min": -1.0,
        "z_max": 1.0,
        "xy_minmax": 1.0,
        "radius": 0.5,
        "geometry_div": 1,
        "gbuffer_cnt": 1,
        "texture_count": 1,
        "texture_size": 256,
        "texture_sampling_count": 1,
        "renderer_variant": 1,
        "alu_calc_count": 4
      },
      "raw_csv": "C:\\Users\\mgkim15\\AppData\\Local\\Temp\\tvbperf_9cgy38ir\\run_00002.csv",
      "individual_csv": "D:\\project\\TVBPerf\\scripts\\results\\scene_geom_ex2\\scene_geom_ex2_runs\\run_00002.csv",
      "artifact_csvs": [
        "D:\\project\\TVBPerf\\scripts\\results\\scene_geom_ex2\\scene_geom_ex2_runs\\run_00002.csv_2_result.csv",
        "D:\\project\\TVBPerf\\scripts\\results\\scene_geom_ex2\\scene_geom_ex2_runs\\run_00002_scene_fingerprint.csv"
      ],
      "raw_row_count": 1,
      "error": "Log saved to: D:\\project\\TVBPerf\\out\\build\\x64-Release\\bin\\Release\\logs\\log_2026-07-23_13-15-12.txt",
      "csv_write_error": null,
      "individual_copy_error": null,
      "artifact_copy_errors": []
    },
    {
      "run_index": 3,
      "repeat": 0,
      "status": "salvaged",
      "started_at": "2026-07-23T13:15:12+09:00",
      "finished_at": "2026-07-23T13:15:15+09:00",
      "return_code": 0,
      "command": [
        "D:\\project\\TVBPerf\\out\\build\\x64-Release\\bin\\Release\\TVBPerf.exe",
        "--run-id",
        "3",
        "--run-name",
        "scene_geom_ex2",
        "--output-filepath",
        "C:\\Users\\mgkim15\\AppData\\Local\\Temp\\tvbperf_9cgy38ir\\run_00003.csv",
        "--renderer-variant",
        "2",
        "--variable",
        "0",
        "--to-use-scene",
        "1",
        "--to-load-texture",
        "0",
        "--use-vfc",
        "1",
        "--scene-path",
        "assets/scenes/unpacked/main_sponza/NewSponza_Main_glTF_003.gltf",
        "--warmup-frames",
        "60",
        "--measure-frames",
        "2400",
        "--auto-terminate",
        "1",
        "--vsync",
        "0",
        "--camera-mode",
        "2",
        "--camera-filepath",
        "standard_camera.csv",
        "--camera-keyframe-interval",
        "10",
        "--to-set-start-frame",
        "0",
        "--key-frame",
        "0",
        "--profile-window-frames",
        "10",
        "--window-width",
        "1920",
        "--window-height",
        "1080",
        "--seed",
        "0",
        "--camera-pos-x",
        "0.0",
        "--camera-pos-y",
        "0.0",
        "--camera-pos-z",
        "-10.0",
        "--camera-lookat-x",
        "0.0",
        "--camera-lookat-y",
        "0.0",
        "--camera-lookat-z",
        "0.0",
        "--camera-near-z",
        "0.1",
        "--camera-far-z",
        "1000.0",
        "--camera-fov",
        "0.785",
        "--object-count",
        "1",
        "--material-count",
        "1",
        "--geometry-count",
        "1",
        "--overdraw-count",
        "0",
        "--to-remain-only-in-camera",
        "0",
        "--z-min",
        "-1.0",
        "--z-max",
        "1.0",
        "--xy-minmax",
        "1.0",
        "--radius",
        "0.5",
        "--geometry-div",
        "1",
        "--gbuffer-cnt",
        "1",
        "--texture-count",
        "1",
        "--texture-size",
        "256",
        "--texture-sampling-count",
        "1",
        "--alu-calc-count",
        "1"
      ],
      "parameters": {
        "run_id": 0,
        "run_name": "no-run-name",
        "output_filepath": "profile_result.csv",
        "variable": 0,
        "to_use_scene": true,
        "to_load_texture": false,
        "use_vfc": true,
        "scene_path": "assets/scenes/unpacked/main_sponza/NewSponza_Main_glTF_003.gltf",
        "warmup_frames": 60,
        "measure_frames": 2400,
        "auto_terminate": true,
        "vsync": false,
        "camera_mode": 2,
        "camera_filepath": "standard_camera.csv",
        "camera_keyframe_interval": 10,
        "to_set_start_frame": false,
        "key_frame": 0,
        "profile_window_frames": 10,
        "window_width": 1920,
        "window_height": 1080,
        "seed": 0,
        "camera_pos_x": 0.0,
        "camera_pos_y": 0.0,
        "camera_pos_z": -10.0,
        "camera_lookat_x": 0.0,
        "camera_lookat_y": 0.0,
        "camera_lookat_z": 0.0,
        "camera_near_z": 0.1,
        "camera_far_z": 1000.0,
        "camera_fov": 0.785,
        "object_count": 1,
        "material_count": 1,
        "geometry_count": 1,
        "overdraw_count": 0,
        "to_remain_only_in_camera": false,
        "z_min": -1.0,
        "z_max": 1.0,
        "xy_minmax": 1.0,
        "radius": 0.5,
        "geometry_div": 1,
        "gbuffer_cnt": 1,
        "texture_count": 1,
        "texture_size": 256,
        "texture_sampling_count": 1,
        "renderer_variant": 2,
        "alu_calc_count": 1
      },
      "raw_csv": "C:\\Users\\mgkim15\\AppData\\Local\\Temp\\tvbperf_9cgy38ir\\run_00003.csv",
      "individual_csv": "D:\\project\\TVBPerf\\scripts\\results\\scene_geom_ex2\\scene_geom_ex2_runs\\run_00003.csv",
      "artifact_csvs": [
        "D:\\project\\TVBPerf\\scripts\\results\\scene_geom_ex2\\scene_geom_ex2_runs\\run_00003.csv_3_result.csv",
        "D:\\project\\TVBPerf\\scripts\\results\\scene_geom_ex2\\scene_geom_ex2_runs\\run_00003_scene_fingerprint.csv"
      ],
      "raw_row_count": 1,
      "error": "Log saved to: D:\\project\\TVBPerf\\out\\build\\x64-Release\\bin\\Release\\logs\\log_2026-07-23_13-15-15.txt",
      "csv_write_error": null,
      "individual_copy_error": null,
      "artifact_copy_errors": []
    },
    {
      "run_index": 4,
      "repeat": 0,
      "status": "salvaged",
      "started_at": "2026-07-23T13:15:15+09:00",
      "finished_at": "2026-07-23T13:15:18+09:00",
      "return_code": 0,
      "command": [
        "D:\\project\\TVBPerf\\out\\build\\x64-Release\\bin\\Release\\TVBPerf.exe",
        "--run-id",
        "4",
        "--run-name",
        "scene_geom_ex2",
        "--output-filepath",
        "C:\\Users\\mgkim15\\AppData\\Local\\Temp\\tvbperf_9cgy38ir\\run_00004.csv",
        "--renderer-variant",
        "2",
        "--variable",
        "0",
        "--to-use-scene",
        "1",
        "--to-load-texture",
        "0",
        "--use-vfc",
        "1",
        "--scene-path",
        "assets/scenes/unpacked/main_sponza/NewSponza_Main_glTF_003.gltf",
        "--warmup-frames",
        "60",
        "--measure-frames",
        "2400",
        "--auto-terminate",
        "1",
        "--vsync",
        "0",
        "--camera-mode",
        "2",
        "--camera-filepath",
        "standard_camera.csv",
        "--camera-keyframe-interval",
        "10",
        "--to-set-start-frame",
        "0",
        "--key-frame",
        "0",
        "--profile-window-frames",
        "10",
        "--window-width",
        "1920",
        "--window-height",
        "1080",
        "--seed",
        "0",
        "--camera-pos-x",
        "0.0",
        "--camera-pos-y",
        "0.0",
        "--camera-pos-z",
        "-10.0",
        "--camera-lookat-x",
        "0.0",
        "--camera-lookat-y",
        "0.0",
        "--camera-lookat-z",
        "0.0",
        "--camera-near-z",
        "0.1",
        "--camera-far-z",
        "1000.0",
        "--camera-fov",
        "0.785",
        "--object-count",
        "1",
        "--material-count",
        "1",
        "--geometry-count",
        "1",
        "--overdraw-count",
        "0",
        "--to-remain-only-in-camera",
        "0",
        "--z-min",
        "-1.0",
        "--z-max",
        "1.0",
        "--xy-minmax",
        "1.0",
        "--radius",
        "0.5",
        "--geometry-div",
        "1",
        "--gbuffer-cnt",
        "1",
        "--texture-count",
        "1",
        "--texture-size",
        "256",
        "--texture-sampling-count",
        "1",
        "--alu-calc-count",
        "2"
      ],
      "parameters": {
        "run_id": 0,
        "run_name": "no-run-name",
        "output_filepath": "profile_result.csv",
        "variable": 0,
        "to_use_scene": true,
        "to_load_texture": false,
        "use_vfc": true,
        "scene_path": "assets/scenes/unpacked/main_sponza/NewSponza_Main_glTF_003.gltf",
        "warmup_frames": 60,
        "measure_frames": 2400,
        "auto_terminate": true,
        "vsync": false,
        "camera_mode": 2,
        "camera_filepath": "standard_camera.csv",
        "camera_keyframe_interval": 10,
        "to_set_start_frame": false,
        "key_frame": 0,
        "profile_window_frames": 10,
        "window_width": 1920,
        "window_height": 1080,
        "seed": 0,
        "camera_pos_x": 0.0,
        "camera_pos_y": 0.0,
        "camera_pos_z": -10.0,
        "camera_lookat_x": 0.0,
        "camera_lookat_y": 0.0,
        "camera_lookat_z": 0.0,
        "camera_near_z": 0.1,
        "camera_far_z": 1000.0,
        "camera_fov": 0.785,
        "object_count": 1,
        "material_count": 1,
        "geometry_count": 1,
        "overdraw_count": 0,
        "to_remain_only_in_camera": false,
        "z_min": -1.0,
        "z_max": 1.0,
        "xy_minmax": 1.0,
        "radius": 0.5,
        "geometry_div": 1,
        "gbuffer_cnt": 1,
        "texture_count": 1,
        "texture_size": 256,
        "texture_sampling_count": 1,
        "renderer_variant": 2,
        "alu_calc_count": 2
      },
      "raw_csv": "C:\\Users\\mgkim15\\AppData\\Local\\Temp\\tvbperf_9cgy38ir\\run_00004.csv",
      "individual_csv": "D:\\project\\TVBPerf\\scripts\\results\\scene_geom_ex2\\scene_geom_ex2_runs\\run_00004.csv",
      "artifact_csvs": [
        "D:\\project\\TVBPerf\\scripts\\results\\scene_geom_ex2\\scene_geom_ex2_runs\\run_00004.csv_4_result.csv",
        "D:\\project\\TVBPerf\\scripts\\results\\scene_geom_ex2\\scene_geom_ex2_runs\\run_00004_scene_fingerprint.csv"
      ],
      "raw_row_count": 1,
      "error": "Log saved to: D:\\project\\TVBPerf\\out\\build\\x64-Release\\bin\\Release\\logs\\log_2026-07-23_13-15-18.txt",
      "csv_write_error": null,
      "individual_copy_error": null,
      "artifact_copy_errors": []
    },
    {
      "run_index": 5,
      "repeat": 0,
      "status": "salvaged",
      "started_at": "2026-07-23T13:15:18+09:00",
      "finished_at": "2026-07-23T13:15:21+09:00",
      "return_code": 0,
      "command": [
        "D:\\project\\TVBPerf\\out\\build\\x64-Release\\bin\\Release\\TVBPerf.exe",
        "--run-id",
        "5",
        "--run-name",
        "scene_geom_ex2",
        "--output-filepath",
        "C:\\Users\\mgkim15\\AppData\\Local\\Temp\\tvbperf_9cgy38ir\\run_00005.csv",
        "--renderer-variant",
        "2",
        "--variable",
        "0",
        "--to-use-scene",
        "1",
        "--to-load-texture",
        "0",
        "--use-vfc",
        "1",
        "--scene-path",
        "assets/scenes/unpacked/main_sponza/NewSponza_Main_glTF_003.gltf",
        "--warmup-frames",
        "60",
        "--measure-frames",
        "2400",
        "--auto-terminate",
        "1",
        "--vsync",
        "0",
        "--camera-mode",
        "2",
        "--camera-filepath",
        "standard_camera.csv",
        "--camera-keyframe-interval",
        "10",
        "--to-set-start-frame",
        "0",
        "--key-frame",
        "0",
        "--profile-window-frames",
        "10",
        "--window-width",
        "1920",
        "--window-height",
        "1080",
        "--seed",
        "0",
        "--camera-pos-x",
        "0.0",
        "--camera-pos-y",
        "0.0",
        "--camera-pos-z",
        "-10.0",
        "--camera-lookat-x",
        "0.0",
        "--camera-lookat-y",
        "0.0",
        "--camera-lookat-z",
        "0.0",
        "--camera-near-z",
        "0.1",
        "--camera-far-z",
        "1000.0",
        "--camera-fov",
        "0.785",
        "--object-count",
        "1",
        "--material-count",
        "1",
        "--geometry-count",
        "1",
        "--overdraw-count",
        "0",
        "--to-remain-only-in-camera",
        "0",
        "--z-min",
        "-1.0",
        "--z-max",
        "1.0",
        "--xy-minmax",
        "1.0",
        "--radius",
        "0.5",
        "--geometry-div",
        "1",
        "--gbuffer-cnt",
        "1",
        "--texture-count",
        "1",
        "--texture-size",
        "256",
        "--texture-sampling-count",
        "1",
        "--alu-calc-count",
        "4"
      ],
      "parameters": {
        "run_id": 0,
        "run_name": "no-run-name",
        "output_filepath": "profile_result.csv",
        "variable": 0,
        "to_use_scene": true,
        "to_load_texture": false,
        "use_vfc": true,
        "scene_path": "assets/scenes/unpacked/main_sponza/NewSponza_Main_glTF_003.gltf",
        "warmup_frames": 60,
        "measure_frames": 2400,
        "auto_terminate": true,
        "vsync": false,
        "camera_mode": 2,
        "camera_filepath": "standard_camera.csv",
        "camera_keyframe_interval": 10,
        "to_set_start_frame": false,
        "key_frame": 0,
        "profile_window_frames": 10,
        "window_width": 1920,
        "window_height": 1080,
        "seed": 0,
        "camera_pos_x": 0.0,
        "camera_pos_y": 0.0,
        "camera_pos_z": -10.0,
        "camera_lookat_x": 0.0,
        "camera_lookat_y": 0.0,
        "camera_lookat_z": 0.0,
        "camera_near_z": 0.1,
        "camera_far_z": 1000.0,
        "camera_fov": 0.785,
        "object_count": 1,
        "material_count": 1,
        "geometry_count": 1,
        "overdraw_count": 0,
        "to_remain_only_in_camera": false,
        "z_min": -1.0,
        "z_max": 1.0,
        "xy_minmax": 1.0,
        "radius": 0.5,
        "geometry_div": 1,
        "gbuffer_cnt": 1,
        "texture_count": 1,
        "texture_size": 256,
        "texture_sampling_count": 1,
        "renderer_variant": 2,
        "alu_calc_count": 4
      },
      "raw_csv": "C:\\Users\\mgkim15\\AppData\\Local\\Temp\\tvbperf_9cgy38ir\\run_00005.csv",
      "individual_csv": "D:\\project\\TVBPerf\\scripts\\results\\scene_geom_ex2\\scene_geom_ex2_runs\\run_00005.csv",
      "artifact_csvs": [
        "D:\\project\\TVBPerf\\scripts\\results\\scene_geom_ex2\\scene_geom_ex2_runs\\run_00005.csv_5_result.csv",
        "D:\\project\\TVBPerf\\scripts\\results\\scene_geom_ex2\\scene_geom_ex2_runs\\run_00005_scene_fingerprint.csv"
      ],
      "raw_row_count": 1,
      "error": "Log saved to: D:\\project\\TVBPerf\\out\\build\\x64-Release\\bin\\Release\\logs\\log_2026-07-23_13-15-21.txt",
      "csv_write_error": null,
      "individual_copy_error": null,
      "artifact_copy_errors": []
    },
    {
      "run_index": 6,
      "repeat": 0,
      "status": "salvaged",
      "started_at": "2026-07-23T13:15:21+09:00",
      "finished_at": "2026-07-23T13:15:24+09:00",
      "return_code": 0,
      "command": [
        "D:\\project\\TVBPerf\\out\\build\\x64-Release\\bin\\Release\\TVBPerf.exe",
        "--run-id",
        "6",
        "--run-name",
        "scene_geom_ex2",
        "--output-filepath",
        "C:\\Users\\mgkim15\\AppData\\Local\\Temp\\tvbperf_9cgy38ir\\run_00006.csv",
        "--renderer-variant",
        "3",
        "--variable",
        "0",
        "--to-use-scene",
        "1",
        "--to-load-texture",
        "0",
        "--use-vfc",
        "1",
        "--scene-path",
        "assets/scenes/unpacked/main_sponza/NewSponza_Main_glTF_003.gltf",
        "--warmup-frames",
        "60",
        "--measure-frames",
        "2400",
        "--auto-terminate",
        "1",
        "--vsync",
        "0",
        "--camera-mode",
        "2",
        "--camera-filepath",
        "standard_camera.csv",
        "--camera-keyframe-interval",
        "10",
        "--to-set-start-frame",
        "0",
        "--key-frame",
        "0",
        "--profile-window-frames",
        "10",
        "--window-width",
        "1920",
        "--window-height",
        "1080",
        "--seed",
        "0",
        "--camera-pos-x",
        "0.0",
        "--camera-pos-y",
        "0.0",
        "--camera-pos-z",
        "-10.0",
        "--camera-lookat-x",
        "0.0",
        "--camera-lookat-y",
        "0.0",
        "--camera-lookat-z",
        "0.0",
        "--camera-near-z",
        "0.1",
        "--camera-far-z",
        "1000.0",
        "--camera-fov",
        "0.785",
        "--object-count",
        "1",
        "--material-count",
        "1",
        "--geometry-count",
        "1",
        "--overdraw-count",
        "0",
        "--to-remain-only-in-camera",
        "0",
        "--z-min",
        "-1.0",
        "--z-max",
        "1.0",
        "--xy-minmax",
        "1.0",
        "--radius",
        "0.5",
        "--geometry-div",
        "1",
        "--gbuffer-cnt",
        "1",
        "--texture-count",
        "1",
        "--texture-size",
        "256",
        "--texture-sampling-count",
        "1",
        "--alu-calc-count",
        "1"
      ],
      "parameters": {
        "run_id": 0,
        "run_name": "no-run-name",
        "output_filepath": "profile_result.csv",
        "variable": 0,
        "to_use_scene": true,
        "to_load_texture": false,
        "use_vfc": true,
        "scene_path": "assets/scenes/unpacked/main_sponza/NewSponza_Main_glTF_003.gltf",
        "warmup_frames": 60,
        "measure_frames": 2400,
        "auto_terminate": true,
        "vsync": false,
        "camera_mode": 2,
        "camera_filepath": "standard_camera.csv",
        "camera_keyframe_interval": 10,
        "to_set_start_frame": false,
        "key_frame": 0,
        "profile_window_frames": 10,
        "window_width": 1920,
        "window_height": 1080,
        "seed": 0,
        "camera_pos_x": 0.0,
        "camera_pos_y": 0.0,
        "camera_pos_z": -10.0,
        "camera_lookat_x": 0.0,
        "camera_lookat_y": 0.0,
        "camera_lookat_z": 0.0,
        "camera_near_z": 0.1,
        "camera_far_z": 1000.0,
        "camera_fov": 0.785,
        "object_count": 1,
        "material_count": 1,
        "geometry_count": 1,
        "overdraw_count": 0,
        "to_remain_only_in_camera": false,
        "z_min": -1.0,
        "z_max": 1.0,
        "xy_minmax": 1.0,
        "radius": 0.5,
        "geometry_div": 1,
        "gbuffer_cnt": 1,
        "texture_count": 1,
        "texture_size": 256,
        "texture_sampling_count": 1,
        "renderer_variant": 3,
        "alu_calc_count": 1
      },
      "raw_csv": "C:\\Users\\mgkim15\\AppData\\Local\\Temp\\tvbperf_9cgy38ir\\run_00006.csv",
      "individual_csv": "D:\\project\\TVBPerf\\scripts\\results\\scene_geom_ex2\\scene_geom_ex2_runs\\run_00006.csv",
      "artifact_csvs": [
        "D:\\project\\TVBPerf\\scripts\\results\\scene_geom_ex2\\scene_geom_ex2_runs\\run_00006.csv_6_result.csv",
        "D:\\project\\TVBPerf\\scripts\\results\\scene_geom_ex2\\scene_geom_ex2_runs\\run_00006_scene_fingerprint.csv"
      ],
      "raw_row_count": 1,
      "error": "Log saved to: D:\\project\\TVBPerf\\out\\build\\x64-Release\\bin\\Release\\logs\\log_2026-07-23_13-15-24.txt",
      "csv_write_error": null,
      "individual_copy_error": null,
      "artifact_copy_errors": []
    },
    {
      "run_index": 7,
      "repeat": 0,
      "status": "salvaged",
      "started_at": "2026-07-23T13:15:24+09:00",
      "finished_at": "2026-07-23T13:15:27+09:00",
      "return_code": 0,
      "command": [
        "D:\\project\\TVBPerf\\out\\build\\x64-Release\\bin\\Release\\TVBPerf.exe",
        "--run-id",
        "7",
        "--run-name",
        "scene_geom_ex2",
        "--output-filepath",
        "C:\\Users\\mgkim15\\AppData\\Local\\Temp\\tvbperf_9cgy38ir\\run_00007.csv",
        "--renderer-variant",
        "3",
        "--variable",
        "0",
        "--to-use-scene",
        "1",
        "--to-load-texture",
        "0",
        "--use-vfc",
        "1",
        "--scene-path",
        "assets/scenes/unpacked/main_sponza/NewSponza_Main_glTF_003.gltf",
        "--warmup-frames",
        "60",
        "--measure-frames",
        "2400",
        "--auto-terminate",
        "1",
        "--vsync",
        "0",
        "--camera-mode",
        "2",
        "--camera-filepath",
        "standard_camera.csv",
        "--camera-keyframe-interval",
        "10",
        "--to-set-start-frame",
        "0",
        "--key-frame",
        "0",
        "--profile-window-frames",
        "10",
        "--window-width",
        "1920",
        "--window-height",
        "1080",
        "--seed",
        "0",
        "--camera-pos-x",
        "0.0",
        "--camera-pos-y",
        "0.0",
        "--camera-pos-z",
        "-10.0",
        "--camera-lookat-x",
        "0.0",
        "--camera-lookat-y",
        "0.0",
        "--camera-lookat-z",
        "0.0",
        "--camera-near-z",
        "0.1",
        "--camera-far-z",
        "1000.0",
        "--camera-fov",
        "0.785",
        "--object-count",
        "1",
        "--material-count",
        "1",
        "--geometry-count",
        "1",
        "--overdraw-count",
        "0",
        "--to-remain-only-in-camera",
        "0",
        "--z-min",
        "-1.0",
        "--z-max",
        "1.0",
        "--xy-minmax",
        "1.0",
        "--radius",
        "0.5",
        "--geometry-div",
        "1",
        "--gbuffer-cnt",
        "1",
        "--texture-count",
        "1",
        "--texture-size",
        "256",
        "--texture-sampling-count",
        "1",
        "--alu-calc-count",
        "2"
      ],
      "parameters": {
        "run_id": 0,
        "run_name": "no-run-name",
        "output_filepath": "profile_result.csv",
        "variable": 0,
        "to_use_scene": true,
        "to_load_texture": false,
        "use_vfc": true,
        "scene_path": "assets/scenes/unpacked/main_sponza/NewSponza_Main_glTF_003.gltf",
        "warmup_frames": 60,
        "measure_frames": 2400,
        "auto_terminate": true,
        "vsync": false,
        "camera_mode": 2,
        "camera_filepath": "standard_camera.csv",
        "camera_keyframe_interval": 10,
        "to_set_start_frame": false,
        "key_frame": 0,
        "profile_window_frames": 10,
        "window_width": 1920,
        "window_height": 1080,
        "seed": 0,
        "camera_pos_x": 0.0,
        "camera_pos_y": 0.0,
        "camera_pos_z": -10.0,
        "camera_lookat_x": 0.0,
        "camera_lookat_y": 0.0,
        "camera_lookat_z": 0.0,
        "camera_near_z": 0.1,
        "camera_far_z": 1000.0,
        "camera_fov": 0.785,
        "object_count": 1,
        "material_count": 1,
        "geometry_count": 1,
        "overdraw_count": 0,
        "to_remain_only_in_camera": false,
        "z_min": -1.0,
        "z_max": 1.0,
        "xy_minmax": 1.0,
        "radius": 0.5,
        "geometry_div": 1,
        "gbuffer_cnt": 1,
        "texture_count": 1,
        "texture_size": 256,
        "texture_sampling_count": 1,
        "renderer_variant": 3,
        "alu_calc_count": 2
      },
      "raw_csv": "C:\\Users\\mgkim15\\AppData\\Local\\Temp\\tvbperf_9cgy38ir\\run_00007.csv",
      "individual_csv": "D:\\project\\TVBPerf\\scripts\\results\\scene_geom_ex2\\scene_geom_ex2_runs\\run_00007.csv",
      "artifact_csvs": [
        "D:\\project\\TVBPerf\\scripts\\results\\scene_geom_ex2\\scene_geom_ex2_runs\\run_00007.csv_7_result.csv",
        "D:\\project\\TVBPerf\\scripts\\results\\scene_geom_ex2\\scene_geom_ex2_runs\\run_00007_scene_fingerprint.csv"
      ],
      "raw_row_count": 1,
      "error": "Log saved to: D:\\project\\TVBPerf\\out\\build\\x64-Release\\bin\\Release\\logs\\log_2026-07-23_13-15-27.txt",
      "csv_write_error": null,
      "individual_copy_error": null,
      "artifact_copy_errors": []
    },
    {
      "run_index": 8,
      "repeat": 0,
      "status": "salvaged",
      "started_at": "2026-07-23T13:15:27+09:00",
      "finished_at": "2026-07-23T13:15:31+09:00",
      "return_code": 0,
      "command": [
        "D:\\project\\TVBPerf\\out\\build\\x64-Release\\bin\\Release\\TVBPerf.exe",
        "--run-id",
        "8",
        "--run-name",
        "scene_geom_ex2",
        "--output-filepath",
        "C:\\Users\\mgkim15\\AppData\\Local\\Temp\\tvbperf_9cgy38ir\\run_00008.csv",
        "--renderer-variant",
        "3",
        "--variable",
        "0",
        "--to-use-scene",
        "1",
        "--to-load-texture",
        "0",
        "--use-vfc",
        "1",
        "--scene-path",
        "assets/scenes/unpacked/main_sponza/NewSponza_Main_glTF_003.gltf",
        "--warmup-frames",
        "60",
        "--measure-frames",
        "2400",
        "--auto-terminate",
        "1",
        "--vsync",
        "0",
        "--camera-mode",
        "2",
        "--camera-filepath",
        "standard_camera.csv",
        "--camera-keyframe-interval",
        "10",
        "--to-set-start-frame",
        "0",
        "--key-frame",
        "0",
        "--profile-window-frames",
        "10",
        "--window-width",
        "1920",
        "--window-height",
        "1080",
        "--seed",
        "0",
        "--camera-pos-x",
        "0.0",
        "--camera-pos-y",
        "0.0",
        "--camera-pos-z",
        "-10.0",
        "--camera-lookat-x",
        "0.0",
        "--camera-lookat-y",
        "0.0",
        "--camera-lookat-z",
        "0.0",
        "--camera-near-z",
        "0.1",
        "--camera-far-z",
        "1000.0",
        "--camera-fov",
        "0.785",
        "--object-count",
        "1",
        "--material-count",
        "1",
        "--geometry-count",
        "1",
        "--overdraw-count",
        "0",
        "--to-remain-only-in-camera",
        "0",
        "--z-min",
        "-1.0",
        "--z-max",
        "1.0",
        "--xy-minmax",
        "1.0",
        "--radius",
        "0.5",
        "--geometry-div",
        "1",
        "--gbuffer-cnt",
        "1",
        "--texture-count",
        "1",
        "--texture-size",
        "256",
        "--texture-sampling-count",
        "1",
        "--alu-calc-count",
        "4"
      ],
      "parameters": {
        "run_id": 0,
        "run_name": "no-run-name",
        "output_filepath": "profile_result.csv",
        "variable": 0,
        "to_use_scene": true,
        "to_load_texture": false,
        "use_vfc": true,
        "scene_path": "assets/scenes/unpacked/main_sponza/NewSponza_Main_glTF_003.gltf",
        "warmup_frames": 60,
        "measure_frames": 2400,
        "auto_terminate": true,
        "vsync": false,
        "camera_mode": 2,
        "camera_filepath": "standard_camera.csv",
        "camera_keyframe_interval": 10,
        "to_set_start_frame": false,
        "key_frame": 0,
        "profile_window_frames": 10,
        "window_width": 1920,
        "window_height": 1080,
        "seed": 0,
        "camera_pos_x": 0.0,
        "camera_pos_y": 0.0,
        "camera_pos_z": -10.0,
        "camera_lookat_x": 0.0,
        "camera_lookat_y": 0.0,
        "camera_lookat_z": 0.0,
        "camera_near_z": 0.1,
        "camera_far_z": 1000.0,
        "camera_fov": 0.785,
        "object_count": 1,
        "material_count": 1,
        "geometry_count": 1,
        "overdraw_count": 0,
        "to_remain_only_in_camera": false,
        "z_min": -1.0,
        "z_max": 1.0,
        "xy_minmax": 1.0,
        "radius": 0.5,
        "geometry_div": 1,
        "gbuffer_cnt": 1,
        "texture_count": 1,
        "texture_size": 256,
        "texture_sampling_count": 1,
        "renderer_variant": 3,
        "alu_calc_count": 4
      },
      "raw_csv": "C:\\Users\\mgkim15\\AppData\\Local\\Temp\\tvbperf_9cgy38ir\\run_00008.csv",
      "individual_csv": "D:\\project\\TVBPerf\\scripts\\results\\scene_geom_ex2\\scene_geom_ex2_runs\\run_00008.csv",
      "artifact_csvs": [
        "D:\\project\\TVBPerf\\scripts\\results\\scene_geom_ex2\\scene_geom_ex2_runs\\run_00008.csv_8_result.csv",
        "D:\\project\\TVBPerf\\scripts\\results\\scene_geom_ex2\\scene_geom_ex2_runs\\run_00008_scene_fingerprint.csv"
      ],
      "raw_row_count": 1,
      "error": "Log saved to: D:\\project\\TVBPerf\\out\\build\\x64-Release\\bin\\Release\\logs\\log_2026-07-23_13-15-31.txt",
      "csv_write_error": null,
      "individual_copy_error": null,
      "artifact_copy_errors": []
    },
    {
      "run_index": 9,
      "repeat": 0,
      "status": "salvaged",
      "started_at": "2026-07-23T13:15:31+09:00",
      "finished_at": "2026-07-23T13:15:34+09:00",
      "return_code": 0,
      "command": [
        "D:\\project\\TVBPerf\\out\\build\\x64-Release\\bin\\Release\\TVBPerf.exe",
        "--run-id",
        "9",
        "--run-name",
        "scene_geom_ex2",
        "--output-filepath",
        "C:\\Users\\mgkim15\\AppData\\Local\\Temp\\tvbperf_9cgy38ir\\run_00009.csv",
        "--renderer-variant",
        "4",
        "--variable",
        "0",
        "--to-use-scene",
        "1",
        "--to-load-texture",
        "0",
        "--use-vfc",
        "1",
        "--scene-path",
        "assets/scenes/unpacked/main_sponza/NewSponza_Main_glTF_003.gltf",
        "--warmup-frames",
        "60",
        "--measure-frames",
        "2400",
        "--auto-terminate",
        "1",
        "--vsync",
        "0",
        "--camera-mode",
        "2",
        "--camera-filepath",
        "standard_camera.csv",
        "--camera-keyframe-interval",
        "10",
        "--to-set-start-frame",
        "0",
        "--key-frame",
        "0",
        "--profile-window-frames",
        "10",
        "--window-width",
        "1920",
        "--window-height",
        "1080",
        "--seed",
        "0",
        "--camera-pos-x",
        "0.0",
        "--camera-pos-y",
        "0.0",
        "--camera-pos-z",
        "-10.0",
        "--camera-lookat-x",
        "0.0",
        "--camera-lookat-y",
        "0.0",
        "--camera-lookat-z",
        "0.0",
        "--camera-near-z",
        "0.1",
        "--camera-far-z",
        "1000.0",
        "--camera-fov",
        "0.785",
        "--object-count",
        "1",
        "--material-count",
        "1",
        "--geometry-count",
        "1",
        "--overdraw-count",
        "0",
        "--to-remain-only-in-camera",
        "0",
        "--z-min",
        "-1.0",
        "--z-max",
        "1.0",
        "--xy-minmax",
        "1.0",
        "--radius",
        "0.5",
        "--geometry-div",
        "1",
        "--gbuffer-cnt",
        "1",
        "--texture-count",
        "1",
        "--texture-size",
        "256",
        "--texture-sampling-count",
        "1",
        "--alu-calc-count",
        "1"
      ],
      "parameters": {
        "run_id": 0,
        "run_name": "no-run-name",
        "output_filepath": "profile_result.csv",
        "variable": 0,
        "to_use_scene": true,
        "to_load_texture": false,
        "use_vfc": true,
        "scene_path": "assets/scenes/unpacked/main_sponza/NewSponza_Main_glTF_003.gltf",
        "warmup_frames": 60,
        "measure_frames": 2400,
        "auto_terminate": true,
        "vsync": false,
        "camera_mode": 2,
        "camera_filepath": "standard_camera.csv",
        "camera_keyframe_interval": 10,
        "to_set_start_frame": false,
        "key_frame": 0,
        "profile_window_frames": 10,
        "window_width": 1920,
        "window_height": 1080,
        "seed": 0,
        "camera_pos_x": 0.0,
        "camera_pos_y": 0.0,
        "camera_pos_z": -10.0,
        "camera_lookat_x": 0.0,
        "camera_lookat_y": 0.0,
        "camera_lookat_z": 0.0,
        "camera_near_z": 0.1,
        "camera_far_z": 1000.0,
        "camera_fov": 0.785,
        "object_count": 1,
        "material_count": 1,
        "geometry_count": 1,
        "overdraw_count": 0,
        "to_remain_only_in_camera": false,
        "z_min": -1.0,
        "z_max": 1.0,
        "xy_minmax": 1.0,
        "radius": 0.5,
        "geometry_div": 1,
        "gbuffer_cnt": 1,
        "texture_count": 1,
        "texture_size": 256,
        "texture_sampling_count": 1,
        "renderer_variant": 4,
        "alu_calc_count": 1
      },
      "raw_csv": "C:\\Users\\mgkim15\\AppData\\Local\\Temp\\tvbperf_9cgy38ir\\run_00009.csv",
      "individual_csv": "D:\\project\\TVBPerf\\scripts\\results\\scene_geom_ex2\\scene_geom_ex2_runs\\run_00009.csv",
      "artifact_csvs": [
        "D:\\project\\TVBPerf\\scripts\\results\\scene_geom_ex2\\scene_geom_ex2_runs\\run_00009.csv_9_result.csv",
        "D:\\project\\TVBPerf\\scripts\\results\\scene_geom_ex2\\scene_geom_ex2_runs\\run_00009_scene_fingerprint.csv"
      ],
      "raw_row_count": 1,
      "error": "Log saved to: D:\\project\\TVBPerf\\out\\build\\x64-Release\\bin\\Release\\logs\\log_2026-07-23_13-15-34.txt",
      "csv_write_error": null,
      "individual_copy_error": null,
      "artifact_copy_errors": []
    },
    {
      "run_index": 10,
      "repeat": 0,
      "status": "salvaged",
      "started_at": "2026-07-23T13:15:34+09:00",
      "finished_at": "2026-07-23T13:15:37+09:00",
      "return_code": 0,
      "command": [
        "D:\\project\\TVBPerf\\out\\build\\x64-Release\\bin\\Release\\TVBPerf.exe",
        "--run-id",
        "10",
        "--run-name",
        "scene_geom_ex2",
        "--output-filepath",
        "C:\\Users\\mgkim15\\AppData\\Local\\Temp\\tvbperf_9cgy38ir\\run_00010.csv",
        "--renderer-variant",
        "4",
        "--variable",
        "0",
        "--to-use-scene",
        "1",
        "--to-load-texture",
        "0",
        "--use-vfc",
        "1",
        "--scene-path",
        "assets/scenes/unpacked/main_sponza/NewSponza_Main_glTF_003.gltf",
        "--warmup-frames",
        "60",
        "--measure-frames",
        "2400",
        "--auto-terminate",
        "1",
        "--vsync",
        "0",
        "--camera-mode",
        "2",
        "--camera-filepath",
        "standard_camera.csv",
        "--camera-keyframe-interval",
        "10",
        "--to-set-start-frame",
        "0",
        "--key-frame",
        "0",
        "--profile-window-frames",
        "10",
        "--window-width",
        "1920",
        "--window-height",
        "1080",
        "--seed",
        "0",
        "--camera-pos-x",
        "0.0",
        "--camera-pos-y",
        "0.0",
        "--camera-pos-z",
        "-10.0",
        "--camera-lookat-x",
        "0.0",
        "--camera-lookat-y",
        "0.0",
        "--camera-lookat-z",
        "0.0",
        "--camera-near-z",
        "0.1",
        "--camera-far-z",
        "1000.0",
        "--camera-fov",
        "0.785",
        "--object-count",
        "1",
        "--material-count",
        "1",
        "--geometry-count",
        "1",
        "--overdraw-count",
        "0",
        "--to-remain-only-in-camera",
        "0",
        "--z-min",
        "-1.0",
        "--z-max",
        "1.0",
        "--xy-minmax",
        "1.0",
        "--radius",
        "0.5",
        "--geometry-div",
        "1",
        "--gbuffer-cnt",
        "1",
        "--texture-count",
        "1",
        "--texture-size",
        "256",
        "--texture-sampling-count",
        "1",
        "--alu-calc-count",
        "2"
      ],
      "parameters": {
        "run_id": 0,
        "run_name": "no-run-name",
        "output_filepath": "profile_result.csv",
        "variable": 0,
        "to_use_scene": true,
        "to_load_texture": false,
        "use_vfc": true,
        "scene_path": "assets/scenes/unpacked/main_sponza/NewSponza_Main_glTF_003.gltf",
        "warmup_frames": 60,
        "measure_frames": 2400,
        "auto_terminate": true,
        "vsync": false,
        "camera_mode": 2,
        "camera_filepath": "standard_camera.csv",
        "camera_keyframe_interval": 10,
        "to_set_start_frame": false,
        "key_frame": 0,
        "profile_window_frames": 10,
        "window_width": 1920,
        "window_height": 1080,
        "seed": 0,
        "camera_pos_x": 0.0,
        "camera_pos_y": 0.0,
        "camera_pos_z": -10.0,
        "camera_lookat_x": 0.0,
        "camera_lookat_y": 0.0,
        "camera_lookat_z": 0.0,
        "camera_near_z": 0.1,
        "camera_far_z": 1000.0,
        "camera_fov": 0.785,
        "object_count": 1,
        "material_count": 1,
        "geometry_count": 1,
        "overdraw_count": 0,
        "to_remain_only_in_camera": false,
        "z_min": -1.0,
        "z_max": 1.0,
        "xy_minmax": 1.0,
        "radius": 0.5,
        "geometry_div": 1,
        "gbuffer_cnt": 1,
        "texture_count": 1,
        "texture_size": 256,
        "texture_sampling_count": 1,
        "renderer_variant": 4,
        "alu_calc_count": 2
      },
      "raw_csv": "C:\\Users\\mgkim15\\AppData\\Local\\Temp\\tvbperf_9cgy38ir\\run_00010.csv",
      "individual_csv": "D:\\project\\TVBPerf\\scripts\\results\\scene_geom_ex2\\scene_geom_ex2_runs\\run_00010.csv",
      "artifact_csvs": [
        "D:\\project\\TVBPerf\\scripts\\results\\scene_geom_ex2\\scene_geom_ex2_runs\\run_00010.csv_10_result.csv",
        "D:\\project\\TVBPerf\\scripts\\results\\scene_geom_ex2\\scene_geom_ex2_runs\\run_00010_scene_fingerprint.csv"
      ],
      "raw_row_count": 1,
      "error": "Log saved to: D:\\project\\TVBPerf\\out\\build\\x64-Release\\bin\\Release\\logs\\log_2026-07-23_13-15-37.txt",
      "csv_write_error": null,
      "individual_copy_error": null,
      "artifact_copy_errors": []
    },
    {
      "run_index": 11,
      "repeat": 0,
      "status": "salvaged",
      "started_at": "2026-07-23T13:15:37+09:00",
      "finished_at": "2026-07-23T13:15:40+09:00",
      "return_code": 0,
      "command": [
        "D:\\project\\TVBPerf\\out\\build\\x64-Release\\bin\\Release\\TVBPerf.exe",
        "--run-id",
        "11",
        "--run-name",
        "scene_geom_ex2",
        "--output-filepath",
        "C:\\Users\\mgkim15\\AppData\\Local\\Temp\\tvbperf_9cgy38ir\\run_00011.csv",
        "--renderer-variant",
        "4",
        "--variable",
        "0",
        "--to-use-scene",
        "1",
        "--to-load-texture",
        "0",
        "--use-vfc",
        "1",
        "--scene-path",
        "assets/scenes/unpacked/main_sponza/NewSponza_Main_glTF_003.gltf",
        "--warmup-frames",
        "60",
        "--measure-frames",
        "2400",
        "--auto-terminate",
        "1",
        "--vsync",
        "0",
        "--camera-mode",
        "2",
        "--camera-filepath",
        "standard_camera.csv",
        "--camera-keyframe-interval",
        "10",
        "--to-set-start-frame",
        "0",
        "--key-frame",
        "0",
        "--profile-window-frames",
        "10",
        "--window-width",
        "1920",
        "--window-height",
        "1080",
        "--seed",
        "0",
        "--camera-pos-x",
        "0.0",
        "--camera-pos-y",
        "0.0",
        "--camera-pos-z",
        "-10.0",
        "--camera-lookat-x",
        "0.0",
        "--camera-lookat-y",
        "0.0",
        "--camera-lookat-z",
        "0.0",
        "--camera-near-z",
        "0.1",
        "--camera-far-z",
        "1000.0",
        "--camera-fov",
        "0.785",
        "--object-count",
        "1",
        "--material-count",
        "1",
        "--geometry-count",
        "1",
        "--overdraw-count",
        "0",
        "--to-remain-only-in-camera",
        "0",
        "--z-min",
        "-1.0",
        "--z-max",
        "1.0",
        "--xy-minmax",
        "1.0",
        "--radius",
        "0.5",
        "--geometry-div",
        "1",
        "--gbuffer-cnt",
        "1",
        "--texture-count",
        "1",
        "--texture-size",
        "256",
        "--texture-sampling-count",
        "1",
        "--alu-calc-count",
        "4"
      ],
      "parameters": {
        "run_id": 0,
        "run_name": "no-run-name",
        "output_filepath": "profile_result.csv",
        "variable": 0,
        "to_use_scene": true,
        "to_load_texture": false,
        "use_vfc": true,
        "scene_path": "assets/scenes/unpacked/main_sponza/NewSponza_Main_glTF_003.gltf",
        "warmup_frames": 60,
        "measure_frames": 2400,
        "auto_terminate": true,
        "vsync": false,
        "camera_mode": 2,
        "camera_filepath": "standard_camera.csv",
        "camera_keyframe_interval": 10,
        "to_set_start_frame": false,
        "key_frame": 0,
        "profile_window_frames": 10,
        "window_width": 1920,
        "window_height": 1080,
        "seed": 0,
        "camera_pos_x": 0.0,
        "camera_pos_y": 0.0,
        "camera_pos_z": -10.0,
        "camera_lookat_x": 0.0,
        "camera_lookat_y": 0.0,
        "camera_lookat_z": 0.0,
        "camera_near_z": 0.1,
        "camera_far_z": 1000.0,
        "camera_fov": 0.785,
        "object_count": 1,
        "material_count": 1,
        "geometry_count": 1,
        "overdraw_count": 0,
        "to_remain_only_in_camera": false,
        "z_min": -1.0,
        "z_max": 1.0,
        "xy_minmax": 1.0,
        "radius": 0.5,
        "geometry_div": 1,
        "gbuffer_cnt": 1,
        "texture_count": 1,
        "texture_size": 256,
        "texture_sampling_count": 1,
        "renderer_variant": 4,
        "alu_calc_count": 4
      },
      "raw_csv": "C:\\Users\\mgkim15\\AppData\\Local\\Temp\\tvbperf_9cgy38ir\\run_00011.csv",
      "individual_csv": "D:\\project\\TVBPerf\\scripts\\results\\scene_geom_ex2\\scene_geom_ex2_runs\\run_00011.csv",
      "artifact_csvs": [
        "D:\\project\\TVBPerf\\scripts\\results\\scene_geom_ex2\\scene_geom_ex2_runs\\run_00011.csv_11_result.csv",
        "D:\\project\\TVBPerf\\scripts\\results\\scene_geom_ex2\\scene_geom_ex2_runs\\run_00011_scene_fingerprint.csv"
      ],
      "raw_row_count": 1,
      "error": "Log saved to: D:\\project\\TVBPerf\\out\\build\\x64-Release\\bin\\Release\\logs\\log_2026-07-23_13-15-40.txt",
      "csv_write_error": null,
      "individual_copy_error": null,
      "artifact_copy_errors": []
    },
    {
      "run_index": 12,
      "repeat": 0,
      "status": "salvaged",
      "started_at": "2026-07-23T13:15:40+09:00",
      "finished_at": "2026-07-23T13:15:44+09:00",
      "return_code": 0,
      "command": [
        "D:\\project\\TVBPerf\\out\\build\\x64-Release\\bin\\Release\\TVBPerf.exe",
        "--run-id",
        "12",
        "--run-name",
        "scene_geom_ex2",
        "--output-filepath",
        "C:\\Users\\mgkim15\\AppData\\Local\\Temp\\tvbperf_9cgy38ir\\run_00012.csv",
        "--renderer-variant",
        "5",
        "--variable",
        "0",
        "--to-use-scene",
        "1",
        "--to-load-texture",
        "0",
        "--use-vfc",
        "1",
        "--scene-path",
        "assets/scenes/unpacked/main_sponza/NewSponza_Main_glTF_003.gltf",
        "--warmup-frames",
        "60",
        "--measure-frames",
        "2400",
        "--auto-terminate",
        "1",
        "--vsync",
        "0",
        "--camera-mode",
        "2",
        "--camera-filepath",
        "standard_camera.csv",
        "--camera-keyframe-interval",
        "10",
        "--to-set-start-frame",
        "0",
        "--key-frame",
        "0",
        "--profile-window-frames",
        "10",
        "--window-width",
        "1920",
        "--window-height",
        "1080",
        "--seed",
        "0",
        "--camera-pos-x",
        "0.0",
        "--camera-pos-y",
        "0.0",
        "--camera-pos-z",
        "-10.0",
        "--camera-lookat-x",
        "0.0",
        "--camera-lookat-y",
        "0.0",
        "--camera-lookat-z",
        "0.0",
        "--camera-near-z",
        "0.1",
        "--camera-far-z",
        "1000.0",
        "--camera-fov",
        "0.785",
        "--object-count",
        "1",
        "--material-count",
        "1",
        "--geometry-count",
        "1",
        "--overdraw-count",
        "0",
        "--to-remain-only-in-camera",
        "0",
        "--z-min",
        "-1.0",
        "--z-max",
        "1.0",
        "--xy-minmax",
        "1.0",
        "--radius",
        "0.5",
        "--geometry-div",
        "1",
        "--gbuffer-cnt",
        "1",
        "--texture-count",
        "1",
        "--texture-size",
        "256",
        "--texture-sampling-count",
        "1",
        "--alu-calc-count",
        "1"
      ],
      "parameters": {
        "run_id": 0,
        "run_name": "no-run-name",
        "output_filepath": "profile_result.csv",
        "variable": 0,
        "to_use_scene": true,
        "to_load_texture": false,
        "use_vfc": true,
        "scene_path": "assets/scenes/unpacked/main_sponza/NewSponza_Main_glTF_003.gltf",
        "warmup_frames": 60,
        "measure_frames": 2400,
        "auto_terminate": true,
        "vsync": false,
        "camera_mode": 2,
        "camera_filepath": "standard_camera.csv",
        "camera_keyframe_interval": 10,
        "to_set_start_frame": false,
        "key_frame": 0,
        "profile_window_frames": 10,
        "window_width": 1920,
        "window_height": 1080,
        "seed": 0,
        "camera_pos_x": 0.0,
        "camera_pos_y": 0.0,
        "camera_pos_z": -10.0,
        "camera_lookat_x": 0.0,
        "camera_lookat_y": 0.0,
        "camera_lookat_z": 0.0,
        "camera_near_z": 0.1,
        "camera_far_z": 1000.0,
        "camera_fov": 0.785,
        "object_count": 1,
        "material_count": 1,
        "geometry_count": 1,
        "overdraw_count": 0,
        "to_remain_only_in_camera": false,
        "z_min": -1.0,
        "z_max": 1.0,
        "xy_minmax": 1.0,
        "radius": 0.5,
        "geometry_div": 1,
        "gbuffer_cnt": 1,
        "texture_count": 1,
        "texture_size": 256,
        "texture_sampling_count": 1,
        "renderer_variant": 5,
        "alu_calc_count": 1
      },
      "raw_csv": "C:\\Users\\mgkim15\\AppData\\Local\\Temp\\tvbperf_9cgy38ir\\run_00012.csv",
      "individual_csv": "D:\\project\\TVBPerf\\scripts\\results\\scene_geom_ex2\\scene_geom_ex2_runs\\run_00012.csv",
      "artifact_csvs": [
        "D:\\project\\TVBPerf\\scripts\\results\\scene_geom_ex2\\scene_geom_ex2_runs\\run_00012.csv_12_result.csv",
        "D:\\project\\TVBPerf\\scripts\\results\\scene_geom_ex2\\scene_geom_ex2_runs\\run_00012_scene_fingerprint.csv"
      ],
      "raw_row_count": 1,
      "error": "Log saved to: D:\\project\\TVBPerf\\out\\build\\x64-Release\\bin\\Release\\logs\\log_2026-07-23_13-15-44.txt",
      "csv_write_error": null,
      "individual_copy_error": null,
      "artifact_copy_errors": []
    },
    {
      "run_index": 13,
      "repeat": 0,
      "status": "salvaged",
      "started_at": "2026-07-23T13:15:44+09:00",
      "finished_at": "2026-07-23T13:15:47+09:00",
      "return_code": 0,
      "command": [
        "D:\\project\\TVBPerf\\out\\build\\x64-Release\\bin\\Release\\TVBPerf.exe",
        "--run-id",
        "13",
        "--run-name",
        "scene_geom_ex2",
        "--output-filepath",
        "C:\\Users\\mgkim15\\AppData\\Local\\Temp\\tvbperf_9cgy38ir\\run_00013.csv",
        "--renderer-variant",
        "5",
        "--variable",
        "0",
        "--to-use-scene",
        "1",
        "--to-load-texture",
        "0",
        "--use-vfc",
        "1",
        "--scene-path",
        "assets/scenes/unpacked/main_sponza/NewSponza_Main_glTF_003.gltf",
        "--warmup-frames",
        "60",
        "--measure-frames",
        "2400",
        "--auto-terminate",
        "1",
        "--vsync",
        "0",
        "--camera-mode",
        "2",
        "--camera-filepath",
        "standard_camera.csv",
        "--camera-keyframe-interval",
        "10",
        "--to-set-start-frame",
        "0",
        "--key-frame",
        "0",
        "--profile-window-frames",
        "10",
        "--window-width",
        "1920",
        "--window-height",
        "1080",
        "--seed",
        "0",
        "--camera-pos-x",
        "0.0",
        "--camera-pos-y",
        "0.0",
        "--camera-pos-z",
        "-10.0",
        "--camera-lookat-x",
        "0.0",
        "--camera-lookat-y",
        "0.0",
        "--camera-lookat-z",
        "0.0",
        "--camera-near-z",
        "0.1",
        "--camera-far-z",
        "1000.0",
        "--camera-fov",
        "0.785",
        "--object-count",
        "1",
        "--material-count",
        "1",
        "--geometry-count",
        "1",
        "--overdraw-count",
        "0",
        "--to-remain-only-in-camera",
        "0",
        "--z-min",
        "-1.0",
        "--z-max",
        "1.0",
        "--xy-minmax",
        "1.0",
        "--radius",
        "0.5",
        "--geometry-div",
        "1",
        "--gbuffer-cnt",
        "1",
        "--texture-count",
        "1",
        "--texture-size",
        "256",
        "--texture-sampling-count",
        "1",
        "--alu-calc-count",
        "2"
      ],
      "parameters": {
        "run_id": 0,
        "run_name": "no-run-name",
        "output_filepath": "profile_result.csv",
        "variable": 0,
        "to_use_scene": true,
        "to_load_texture": false,
        "use_vfc": true,
        "scene_path": "assets/scenes/unpacked/main_sponza/NewSponza_Main_glTF_003.gltf",
        "warmup_frames": 60,
        "measure_frames": 2400,
        "auto_terminate": true,
        "vsync": false,
        "camera_mode": 2,
        "camera_filepath": "standard_camera.csv",
        "camera_keyframe_interval": 10,
        "to_set_start_frame": false,
        "key_frame": 0,
        "profile_window_frames": 10,
        "window_width": 1920,
        "window_height": 1080,
        "seed": 0,
        "camera_pos_x": 0.0,
        "camera_pos_y": 0.0,
        "camera_pos_z": -10.0,
        "camera_lookat_x": 0.0,
        "camera_lookat_y": 0.0,
        "camera_lookat_z": 0.0,
        "camera_near_z": 0.1,
        "camera_far_z": 1000.0,
        "camera_fov": 0.785,
        "object_count": 1,
        "material_count": 1,
        "geometry_count": 1,
        "overdraw_count": 0,
        "to_remain_only_in_camera": false,
        "z_min": -1.0,
        "z_max": 1.0,
        "xy_minmax": 1.0,
        "radius": 0.5,
        "geometry_div": 1,
        "gbuffer_cnt": 1,
        "texture_count": 1,
        "texture_size": 256,
        "texture_sampling_count": 1,
        "renderer_variant": 5,
        "alu_calc_count": 2
      },
      "raw_csv": "C:\\Users\\mgkim15\\AppData\\Local\\Temp\\tvbperf_9cgy38ir\\run_00013.csv",
      "individual_csv": "D:\\project\\TVBPerf\\scripts\\results\\scene_geom_ex2\\scene_geom_ex2_runs\\run_00013.csv",
      "artifact_csvs": [
        "D:\\project\\TVBPerf\\scripts\\results\\scene_geom_ex2\\scene_geom_ex2_runs\\run_00013.csv_13_result.csv",
        "D:\\project\\TVBPerf\\scripts\\results\\scene_geom_ex2\\scene_geom_ex2_runs\\run_00013_scene_fingerprint.csv"
      ],
      "raw_row_count": 1,
      "error": "Log saved to: D:\\project\\TVBPerf\\out\\build\\x64-Release\\bin\\Release\\logs\\log_2026-07-23_13-15-47.txt",
      "csv_write_error": null,
      "individual_copy_error": null,
      "artifact_copy_errors": []
    },
    {
      "run_index": 14,
      "repeat": 0,
      "status": "salvaged",
      "started_at": "2026-07-23T13:15:47+09:00",
      "finished_at": "2026-07-23T13:15:50+09:00",
      "return_code": 0,
      "command": [
        "D:\\project\\TVBPerf\\out\\build\\x64-Release\\bin\\Release\\TVBPerf.exe",
        "--run-id",
        "14",
        "--run-name",
        "scene_geom_ex2",
        "--output-filepath",
        "C:\\Users\\mgkim15\\AppData\\Local\\Temp\\tvbperf_9cgy38ir\\run_00014.csv",
        "--renderer-variant",
        "5",
        "--variable",
        "0",
        "--to-use-scene",
        "1",
        "--to-load-texture",
        "0",
        "--use-vfc",
        "1",
        "--scene-path",
        "assets/scenes/unpacked/main_sponza/NewSponza_Main_glTF_003.gltf",
        "--warmup-frames",
        "60",
        "--measure-frames",
        "2400",
        "--auto-terminate",
        "1",
        "--vsync",
        "0",
        "--camera-mode",
        "2",
        "--camera-filepath",
        "standard_camera.csv",
        "--camera-keyframe-interval",
        "10",
        "--to-set-start-frame",
        "0",
        "--key-frame",
        "0",
        "--profile-window-frames",
        "10",
        "--window-width",
        "1920",
        "--window-height",
        "1080",
        "--seed",
        "0",
        "--camera-pos-x",
        "0.0",
        "--camera-pos-y",
        "0.0",
        "--camera-pos-z",
        "-10.0",
        "--camera-lookat-x",
        "0.0",
        "--camera-lookat-y",
        "0.0",
        "--camera-lookat-z",
        "0.0",
        "--camera-near-z",
        "0.1",
        "--camera-far-z",
        "1000.0",
        "--camera-fov",
        "0.785",
        "--object-count",
        "1",
        "--material-count",
        "1",
        "--geometry-count",
        "1",
        "--overdraw-count",
        "0",
        "--to-remain-only-in-camera",
        "0",
        "--z-min",
        "-1.0",
        "--z-max",
        "1.0",
        "--xy-minmax",
        "1.0",
        "--radius",
        "0.5",
        "--geometry-div",
        "1",
        "--gbuffer-cnt",
        "1",
        "--texture-count",
        "1",
        "--texture-size",
        "256",
        "--texture-sampling-count",
        "1",
        "--alu-calc-count",
        "4"
      ],
      "parameters": {
        "run_id": 0,
        "run_name": "no-run-name",
        "output_filepath": "profile_result.csv",
        "variable": 0,
        "to_use_scene": true,
        "to_load_texture": false,
        "use_vfc": true,
        "scene_path": "assets/scenes/unpacked/main_sponza/NewSponza_Main_glTF_003.gltf",
        "warmup_frames": 60,
        "measure_frames": 2400,
        "auto_terminate": true,
        "vsync": false,
        "camera_mode": 2,
        "camera_filepath": "standard_camera.csv",
        "camera_keyframe_interval": 10,
        "to_set_start_frame": false,
        "key_frame": 0,
        "profile_window_frames": 10,
        "window_width": 1920,
        "window_height": 1080,
        "seed": 0,
        "camera_pos_x": 0.0,
        "camera_pos_y": 0.0,
        "camera_pos_z": -10.0,
        "camera_lookat_x": 0.0,
        "camera_lookat_y": 0.0,
        "camera_lookat_z": 0.0,
        "camera_near_z": 0.1,
        "camera_far_z": 1000.0,
        "camera_fov": 0.785,
        "object_count": 1,
        "material_count": 1,
        "geometry_count": 1,
        "overdraw_count": 0,
        "to_remain_only_in_camera": false,
        "z_min": -1.0,
        "z_max": 1.0,
        "xy_minmax": 1.0,
        "radius": 0.5,
        "geometry_div": 1,
        "gbuffer_cnt": 1,
        "texture_count": 1,
        "texture_size": 256,
        "texture_sampling_count": 1,
        "renderer_variant": 5,
        "alu_calc_count": 4
      },
      "raw_csv": "C:\\Users\\mgkim15\\AppData\\Local\\Temp\\tvbperf_9cgy38ir\\run_00014.csv",
      "individual_csv": "D:\\project\\TVBPerf\\scripts\\results\\scene_geom_ex2\\scene_geom_ex2_runs\\run_00014.csv",
      "artifact_csvs": [
        "D:\\project\\TVBPerf\\scripts\\results\\scene_geom_ex2\\scene_geom_ex2_runs\\run_00014.csv_14_result.csv",
        "D:\\project\\TVBPerf\\scripts\\results\\scene_geom_ex2\\scene_geom_ex2_runs\\run_00014_scene_fingerprint.csv"
      ],
      "raw_row_count": 1,
      "error": "Log saved to: D:\\project\\TVBPerf\\out\\build\\x64-Release\\bin\\Release\\logs\\log_2026-07-23_13-15-50.txt",
      "csv_write_error": null,
      "individual_copy_error": null,
      "artifact_copy_errors": []
    },
    {
      "run_index": 15,
      "repeat": 0,
      "status": "salvaged",
      "started_at": "2026-07-23T13:15:50+09:00",
      "finished_at": "2026-07-23T13:15:54+09:00",
      "return_code": 0,
      "command": [
        "D:\\project\\TVBPerf\\out\\build\\x64-Release\\bin\\Release\\TVBPerf.exe",
        "--run-id",
        "15",
        "--run-name",
        "scene_geom_ex2",
        "--output-filepath",
        "C:\\Users\\mgkim15\\AppData\\Local\\Temp\\tvbperf_9cgy38ir\\run_00015.csv",
        "--renderer-variant",
        "6",
        "--variable",
        "0",
        "--to-use-scene",
        "1",
        "--to-load-texture",
        "0",
        "--use-vfc",
        "1",
        "--scene-path",
        "assets/scenes/unpacked/main_sponza/NewSponza_Main_glTF_003.gltf",
        "--warmup-frames",
        "60",
        "--measure-frames",
        "2400",
        "--auto-terminate",
        "1",
        "--vsync",
        "0",
        "--camera-mode",
        "2",
        "--camera-filepath",
        "standard_camera.csv",
        "--camera-keyframe-interval",
        "10",
        "--to-set-start-frame",
        "0",
        "--key-frame",
        "0",
        "--profile-window-frames",
        "10",
        "--window-width",
        "1920",
        "--window-height",
        "1080",
        "--seed",
        "0",
        "--camera-pos-x",
        "0.0",
        "--camera-pos-y",
        "0.0",
        "--camera-pos-z",
        "-10.0",
        "--camera-lookat-x",
        "0.0",
        "--camera-lookat-y",
        "0.0",
        "--camera-lookat-z",
        "0.0",
        "--camera-near-z",
        "0.1",
        "--camera-far-z",
        "1000.0",
        "--camera-fov",
        "0.785",
        "--object-count",
        "1",
        "--material-count",
        "1",
        "--geometry-count",
        "1",
        "--overdraw-count",
        "0",
        "--to-remain-only-in-camera",
        "0",
        "--z-min",
        "-1.0",
        "--z-max",
        "1.0",
        "--xy-minmax",
        "1.0",
        "--radius",
        "0.5",
        "--geometry-div",
        "1",
        "--gbuffer-cnt",
        "1",
        "--texture-count",
        "1",
        "--texture-size",
        "256",
        "--texture-sampling-count",
        "1",
        "--alu-calc-count",
        "1"
      ],
      "parameters": {
        "run_id": 0,
        "run_name": "no-run-name",
        "output_filepath": "profile_result.csv",
        "variable": 0,
        "to_use_scene": true,
        "to_load_texture": false,
        "use_vfc": true,
        "scene_path": "assets/scenes/unpacked/main_sponza/NewSponza_Main_glTF_003.gltf",
        "warmup_frames": 60,
        "measure_frames": 2400,
        "auto_terminate": true,
        "vsync": false,
        "camera_mode": 2,
        "camera_filepath": "standard_camera.csv",
        "camera_keyframe_interval": 10,
        "to_set_start_frame": false,
        "key_frame": 0,
        "profile_window_frames": 10,
        "window_width": 1920,
        "window_height": 1080,
        "seed": 0,
        "camera_pos_x": 0.0,
        "camera_pos_y": 0.0,
        "camera_pos_z": -10.0,
        "camera_lookat_x": 0.0,
        "camera_lookat_y": 0.0,
        "camera_lookat_z": 0.0,
        "camera_near_z": 0.1,
        "camera_far_z": 1000.0,
        "camera_fov": 0.785,
        "object_count": 1,
        "material_count": 1,
        "geometry_count": 1,
        "overdraw_count": 0,
        "to_remain_only_in_camera": false,
        "z_min": -1.0,
        "z_max": 1.0,
        "xy_minmax": 1.0,
        "radius": 0.5,
        "geometry_div": 1,
        "gbuffer_cnt": 1,
        "texture_count": 1,
        "texture_size": 256,
        "texture_sampling_count": 1,
        "renderer_variant": 6,
        "alu_calc_count": 1
      },
      "raw_csv": "C:\\Users\\mgkim15\\AppData\\Local\\Temp\\tvbperf_9cgy38ir\\run_00015.csv",
      "individual_csv": "D:\\project\\TVBPerf\\scripts\\results\\scene_geom_ex2\\scene_geom_ex2_runs\\run_00015.csv",
      "artifact_csvs": [
        "D:\\project\\TVBPerf\\scripts\\results\\scene_geom_ex2\\scene_geom_ex2_runs\\run_00015.csv_15_result.csv",
        "D:\\project\\TVBPerf\\scripts\\results\\scene_geom_ex2\\scene_geom_ex2_runs\\run_00015_scene_fingerprint.csv"
      ],
      "raw_row_count": 1,
      "error": "Log saved to: D:\\project\\TVBPerf\\out\\build\\x64-Release\\bin\\Release\\logs\\log_2026-07-23_13-15-54.txt",
      "csv_write_error": null,
      "individual_copy_error": null,
      "artifact_copy_errors": []
    },
    {
      "run_index": 16,
      "repeat": 0,
      "status": "salvaged",
      "started_at": "2026-07-23T13:15:54+09:00",
      "finished_at": "2026-07-23T13:15:57+09:00",
      "return_code": 0,
      "command": [
        "D:\\project\\TVBPerf\\out\\build\\x64-Release\\bin\\Release\\TVBPerf.exe",
        "--run-id",
        "16",
        "--run-name",
        "scene_geom_ex2",
        "--output-filepath",
        "C:\\Users\\mgkim15\\AppData\\Local\\Temp\\tvbperf_9cgy38ir\\run_00016.csv",
        "--renderer-variant",
        "6",
        "--variable",
        "0",
        "--to-use-scene",
        "1",
        "--to-load-texture",
        "0",
        "--use-vfc",
        "1",
        "--scene-path",
        "assets/scenes/unpacked/main_sponza/NewSponza_Main_glTF_003.gltf",
        "--warmup-frames",
        "60",
        "--measure-frames",
        "2400",
        "--auto-terminate",
        "1",
        "--vsync",
        "0",
        "--camera-mode",
        "2",
        "--camera-filepath",
        "standard_camera.csv",
        "--camera-keyframe-interval",
        "10",
        "--to-set-start-frame",
        "0",
        "--key-frame",
        "0",
        "--profile-window-frames",
        "10",
        "--window-width",
        "1920",
        "--window-height",
        "1080",
        "--seed",
        "0",
        "--camera-pos-x",
        "0.0",
        "--camera-pos-y",
        "0.0",
        "--camera-pos-z",
        "-10.0",
        "--camera-lookat-x",
        "0.0",
        "--camera-lookat-y",
        "0.0",
        "--camera-lookat-z",
        "0.0",
        "--camera-near-z",
        "0.1",
        "--camera-far-z",
        "1000.0",
        "--camera-fov",
        "0.785",
        "--object-count",
        "1",
        "--material-count",
        "1",
        "--geometry-count",
        "1",
        "--overdraw-count",
        "0",
        "--to-remain-only-in-camera",
        "0",
        "--z-min",
        "-1.0",
        "--z-max",
        "1.0",
        "--xy-minmax",
        "1.0",
        "--radius",
        "0.5",
        "--geometry-div",
        "1",
        "--gbuffer-cnt",
        "1",
        "--texture-count",
        "1",
        "--texture-size",
        "256",
        "--texture-sampling-count",
        "1",
        "--alu-calc-count",
        "2"
      ],
      "parameters": {
        "run_id": 0,
        "run_name": "no-run-name",
        "output_filepath": "profile_result.csv",
        "variable": 0,
        "to_use_scene": true,
        "to_load_texture": false,
        "use_vfc": true,
        "scene_path": "assets/scenes/unpacked/main_sponza/NewSponza_Main_glTF_003.gltf",
        "warmup_frames": 60,
        "measure_frames": 2400,
        "auto_terminate": true,
        "vsync": false,
        "camera_mode": 2,
        "camera_filepath": "standard_camera.csv",
        "camera_keyframe_interval": 10,
        "to_set_start_frame": false,
        "key_frame": 0,
        "profile_window_frames": 10,
        "window_width": 1920,
        "window_height": 1080,
        "seed": 0,
        "camera_pos_x": 0.0,
        "camera_pos_y": 0.0,
        "camera_pos_z": -10.0,
        "camera_lookat_x": 0.0,
        "camera_lookat_y": 0.0,
        "camera_lookat_z": 0.0,
        "camera_near_z": 0.1,
        "camera_far_z": 1000.0,
        "camera_fov": 0.785,
        "object_count": 1,
        "material_count": 1,
        "geometry_count": 1,
        "overdraw_count": 0,
        "to_remain_only_in_camera": false,
        "z_min": -1.0,
        "z_max": 1.0,
        "xy_minmax": 1.0,
        "radius": 0.5,
        "geometry_div": 1,
        "gbuffer_cnt": 1,
        "texture_count": 1,
        "texture_size": 256,
        "texture_sampling_count": 1,
        "renderer_variant": 6,
        "alu_calc_count": 2
      },
      "raw_csv": "C:\\Users\\mgkim15\\AppData\\Local\\Temp\\tvbperf_9cgy38ir\\run_00016.csv",
      "individual_csv": "D:\\project\\TVBPerf\\scripts\\results\\scene_geom_ex2\\scene_geom_ex2_runs\\run_00016.csv",
      "artifact_csvs": [
        "D:\\project\\TVBPerf\\scripts\\results\\scene_geom_ex2\\scene_geom_ex2_runs\\run_00016.csv_16_result.csv",
        "D:\\project\\TVBPerf\\scripts\\results\\scene_geom_ex2\\scene_geom_ex2_runs\\run_00016_scene_fingerprint.csv"
      ],
      "raw_row_count": 1,
      "error": "Log saved to: D:\\project\\TVBPerf\\out\\build\\x64-Release\\bin\\Release\\logs\\log_2026-07-23_13-15-57.txt",
      "csv_write_error": null,
      "individual_copy_error": null,
      "artifact_copy_errors": []
    },
    {
      "run_index": 17,
      "repeat": 0,
      "status": "salvaged",
      "started_at": "2026-07-23T13:15:57+09:00",
      "finished_at": "2026-07-23T13:16:00+09:00",
      "return_code": 0,
      "command": [
        "D:\\project\\TVBPerf\\out\\build\\x64-Release\\bin\\Release\\TVBPerf.exe",
        "--run-id",
        "17",
        "--run-name",
        "scene_geom_ex2",
        "--output-filepath",
        "C:\\Users\\mgkim15\\AppData\\Local\\Temp\\tvbperf_9cgy38ir\\run_00017.csv",
        "--renderer-variant",
        "6",
        "--variable",
        "0",
        "--to-use-scene",
        "1",
        "--to-load-texture",
        "0",
        "--use-vfc",
        "1",
        "--scene-path",
        "assets/scenes/unpacked/main_sponza/NewSponza_Main_glTF_003.gltf",
        "--warmup-frames",
        "60",
        "--measure-frames",
        "2400",
        "--auto-terminate",
        "1",
        "--vsync",
        "0",
        "--camera-mode",
        "2",
        "--camera-filepath",
        "standard_camera.csv",
        "--camera-keyframe-interval",
        "10",
        "--to-set-start-frame",
        "0",
        "--key-frame",
        "0",
        "--profile-window-frames",
        "10",
        "--window-width",
        "1920",
        "--window-height",
        "1080",
        "--seed",
        "0",
        "--camera-pos-x",
        "0.0",
        "--camera-pos-y",
        "0.0",
        "--camera-pos-z",
        "-10.0",
        "--camera-lookat-x",
        "0.0",
        "--camera-lookat-y",
        "0.0",
        "--camera-lookat-z",
        "0.0",
        "--camera-near-z",
        "0.1",
        "--camera-far-z",
        "1000.0",
        "--camera-fov",
        "0.785",
        "--object-count",
        "1",
        "--material-count",
        "1",
        "--geometry-count",
        "1",
        "--overdraw-count",
        "0",
        "--to-remain-only-in-camera",
        "0",
        "--z-min",
        "-1.0",
        "--z-max",
        "1.0",
        "--xy-minmax",
        "1.0",
        "--radius",
        "0.5",
        "--geometry-div",
        "1",
        "--gbuffer-cnt",
        "1",
        "--texture-count",
        "1",
        "--texture-size",
        "256",
        "--texture-sampling-count",
        "1",
        "--alu-calc-count",
        "4"
      ],
      "parameters": {
        "run_id": 0,
        "run_name": "no-run-name",
        "output_filepath": "profile_result.csv",
        "variable": 0,
        "to_use_scene": true,
        "to_load_texture": false,
        "use_vfc": true,
        "scene_path": "assets/scenes/unpacked/main_sponza/NewSponza_Main_glTF_003.gltf",
        "warmup_frames": 60,
        "measure_frames": 2400,
        "auto_terminate": true,
        "vsync": false,
        "camera_mode": 2,
        "camera_filepath": "standard_camera.csv",
        "camera_keyframe_interval": 10,
        "to_set_start_frame": false,
        "key_frame": 0,
        "profile_window_frames": 10,
        "window_width": 1920,
        "window_height": 1080,
        "seed": 0,
        "camera_pos_x": 0.0,
        "camera_pos_y": 0.0,
        "camera_pos_z": -10.0,
        "camera_lookat_x": 0.0,
        "camera_lookat_y": 0.0,
        "camera_lookat_z": 0.0,
        "camera_near_z": 0.1,
        "camera_far_z": 1000.0,
        "camera_fov": 0.785,
        "object_count": 1,
        "material_count": 1,
        "geometry_count": 1,
        "overdraw_count": 0,
        "to_remain_only_in_camera": false,
        "z_min": -1.0,
        "z_max": 1.0,
        "xy_minmax": 1.0,
        "radius": 0.5,
        "geometry_div": 1,
        "gbuffer_cnt": 1,
        "texture_count": 1,
        "texture_size": 256,
        "texture_sampling_count": 1,
        "renderer_variant": 6,
        "alu_calc_count": 4
      },
      "raw_csv": "C:\\Users\\mgkim15\\AppData\\Local\\Temp\\tvbperf_9cgy38ir\\run_00017.csv",
      "individual_csv": "D:\\project\\TVBPerf\\scripts\\results\\scene_geom_ex2\\scene_geom_ex2_runs\\run_00017.csv",
      "artifact_csvs": [
        "D:\\project\\TVBPerf\\scripts\\results\\scene_geom_ex2\\scene_geom_ex2_runs\\run_00017.csv_17_result.csv",
        "D:\\project\\TVBPerf\\scripts\\results\\scene_geom_ex2\\scene_geom_ex2_runs\\run_00017_scene_fingerprint.csv"
      ],
      "raw_row_count": 1,
      "error": "Log saved to: D:\\project\\TVBPerf\\out\\build\\x64-Release\\bin\\Release\\logs\\log_2026-07-23_13-16-00.txt",
      "csv_write_error": null,
      "individual_copy_error": null,
      "artifact_copy_errors": []
    }
  ],
  "fatal_error": null,
  "spec_copy_error": null,
  "experiment": "scene_geom_ex2",
  "executable": "D:\\project\\TVBPerf\\out\\build\\x64-Release\\bin\\Release\\TVBPerf.exe",
  "parameter_source": "sweep",
  "parameter_set_count": 18,
  "total_runs": 18
}
